{".class": "MypyFile", "_fullname": "fishnet_cod.core.execution", "future_import_flags": [], "is_partial_stub_package": false, "is_stub": false, "names": {".class": "SymbolTable", "Algorithm": {".class": "SymbolTableNode", "cross_ref": "fishnet_cod.core.model.Algorithm", "kind": "Gdef"}, "Any": {".class": "SymbolTableNode", "cross_ref": "typing.Any", "kind": "Gdef"}, "Dataset": {".class": "SymbolTableNode", "cross_ref": "fishnet_cod.core.model.Dataset", "kind": "Gdef"}, "DatasetPermissionStatus": {".class": "SymbolTableNode", "cross_ref": "fishnet_cod.core.model.DatasetPermissionStatus", "kind": "Gdef"}, "Dict": {".class": "SymbolTableNode", "cross_ref": "typing.Dict", "kind": "Gdef"}, "Enum": {".class": "SymbolTableNode", "cross_ref": "enum.Enum", "kind": "Gdef"}, "Execution": {".class": "SymbolTableNode", "cross_ref": "fishnet_cod.core.model.Execution", "kind": "Gdef"}, "ExecutionStatus": {".class": "SymbolTableNode", "cross_ref": "fishnet_cod.core.model.ExecutionStatus", "kind": "Gdef"}, "Granularity": {".class": "SymbolTableNode", "cross_ref": "fishnet_cod.core.model.Granularity", "kind": "Gdef"}, "List": {".class": "SymbolTableNode", "cross_ref": "typing.List", "kind": "Gdef"}, "Optional": {".class": "SymbolTableNode", "cross_ref": "typing.Optional", "kind": "Gdef"}, "Permission": {".class": "SymbolTableNode", "cross_ref": "fishnet_cod.core.model.Permission", "kind": "Gdef"}, "PermissionStatus": {".class": "SymbolTableNode", "cross_ref": "fishnet_cod.core.model.PermissionStatus", "kind": "Gdef"}, "PostMessage": {".class": "SymbolTableNode", "kind": "Gdef", "node": {".class": "Var", "flags": ["is_suppressed_import", "is_ready", "is_inferred"], "fullname": "fishnet_cod.core.execution.PostMessage", "name": "PostMessage", "type": {".class": "AnyType", "missing_import_name": "fishnet_cod.core.execution.PostMessage", "source_any": null, "type_of_any": 3}}}, "Record": {".class": "SymbolTableNode", "cross_ref": "fishnet_cod.core.model.Record", "kind": "Gdef"}, "Result": {".class": "SymbolTableNode", "cross_ref": "fishnet_cod.core.model.Result", "kind": "Gdef"}, "Timeseries": {".class": "SymbolTableNode", "cross_ref": "fishnet_cod.core.model.Timeseries", "kind": "Gdef"}, "Tuple": {".class": "SymbolTableNode", "cross_ref": "typing.Tuple", "kind": "Gdef"}, "UserInfo": {".class": "SymbolTableNode", "cross_ref": "fishnet_cod.core.model.UserInfo", "kind": "Gdef"}, "ValidationError": {".class": "SymbolTableNode", "cross_ref": "pydantic.error_wrappers.ValidationError", "kind": "Gdef"}, "View": {".class": "SymbolTableNode", "cross_ref": "fishnet_cod.core.model.View", "kind": "Gdef"}, "__annotations__": {".class": "SymbolTableNode", "kind": "Gdef", "node": {".class": "Var", "flags": ["is_ready"], "fullname": "fishnet_cod.core.execution.__annotations__", "name": "__annotations__", "type": {".class": "Instance", "args": ["builtins.str", {".class": "AnyType", "missing_import_name": null, "source_any": null, "type_of_any": 6}], "type_ref": "builtins.dict"}}}, "__doc__": {".class": "SymbolTableNode", "kind": "Gdef", "node": {".class": "Var", "flags": ["is_ready"], "fullname": "fishnet_cod.core.execution.__doc__", "name": "__doc__", "type": "builtins.str"}}, "__file__": {".class": "SymbolTableNode", "kind": "Gdef", "node": {".class": "Var", "flags": ["is_ready"], "fullname": "fishnet_cod.core.execution.__file__", "name": "__file__", "type": "builtins.str"}}, "__name__": {".class": "SymbolTableNode", "kind": "Gdef", "node": {".class": "Var", "flags": ["is_ready"], "fullname": "fishnet_cod.core.execution.__name__", "name": "__name__", "type": "builtins.str"}}, "__package__": {".class": "SymbolTableNode", "kind": "Gdef", "node": {".class": "Var", "flags": ["is_ready"], "fullname": "fishnet_cod.core.execution.__package__", "name": "__package__", "type": "builtins.str"}}, "pd": {".class": "SymbolTableNode", "kind": "Gdef", "node": {".class": "Var", "flags": ["is_suppressed_import", "is_ready", "is_inferred"], "fullname": "fishnet_cod.core.execution.pd", "name": "pd", "type": {".class": "AnyType", "missing_import_name": "fishnet_cod.core.execution.pd", "source_any": null, "type_of_any": 3}}}, "run_execution": {".class": "SymbolTableNode", "kind": "Gdef", "node": {".class": "FuncDef", "abstract_status": 0, "arg_kinds": [0], "arg_names": ["execution"], "dataclass_transform_spec": null, "flags": ["is_coroutine"], "fullname": "fishnet_cod.core.execution.run_execution", "name": "run_execution", "type": {".class": "CallableType", "arg_kinds": [0], "arg_names": ["execution"], "arg_types": ["fishnet_cod.core.model.Execution"], "bound_args": [], "def_extras": {"first_arg": null}, "fallback": "builtins.function", "from_concatenate": false, "implicit": false, "is_ellipsis_args": false, "name": "run_execution", "ret_type": {".class": "Instance", "args": [{".class": "AnyType", "missing_import_name": null, "source_any": null, "type_of_any": 6}, {".class": "AnyType", "missing_import_name": null, "source_any": null, "type_of_any": 6}, {".class": "UnionType", "items": ["fishnet_cod.core.model.Execution", {".class": "NoneType"}]}], "type_ref": "typing.Coroutine"}, "type_guard": null, "unpack_kwargs": false, "variables": []}}}, "try_get_execution_from_message": {".class": "SymbolTableNode", "kind": "Gdef", "node": {".class": "FuncDef", "abstract_status": 0, "arg_kinds": [0], "arg_names": ["message"], "dataclass_transform_spec": null, "flags": ["is_coroutine"], "fullname": "fishnet_cod.core.execution.try_get_execution_from_message", "name": "try_get_execution_from_message", "type": {".class": "CallableType", "arg_kinds": [0], "arg_names": ["message"], "arg_types": [{".class": "AnyType", "missing_import_name": "fishnet_cod.core.execution.PostMessage", "source_any": null, "type_of_any": 3}], "bound_args": [], "def_extras": {"first_arg": null}, "fallback": "builtins.function", "from_concatenate": false, "implicit": false, "is_ellipsis_args": false, "name": "try_get_execution_from_message", "ret_type": {".class": "Instance", "args": [{".class": "AnyType", "missing_import_name": null, "source_any": null, "type_of_any": 6}, {".class": "AnyType", "missing_import_name": null, "source_any": null, "type_of_any": 6}, {".class": "UnionType", "items": ["fishnet_cod.core.model.Execution", {".class": "NoneType"}]}], "type_ref": "typing.Coroutine"}, "type_guard": null, "unpack_kwargs": false, "variables": []}}}}, "path": "/home/mik/PycharmProjects/yourtrading-ai/fishnet-cod/src/fishnet_cod/core/execution.py"}